container_manager/__init__.py
container_manager/admin.py
container_manager/apps.py
container_manager/bulk_operations.py
container_manager/defaults.py
container_manager/exceptions.py
container_manager/models.py
container_manager/queue.py
container_manager/retry.py
container_manager/services.py
container_manager/signals.py
container_manager/views.py
container_manager/executors/__init__.py
container_manager/executors/base.py
container_manager/executors/cloudrun.py
container_manager/executors/docker.py
container_manager/executors/exceptions.py
container_manager/executors/factory.py
container_manager/executors/mock.py
container_manager/management/__init__.py
container_manager/management/commands/__init__.py
container_manager/management/commands/cleanup_containers.py
container_manager/management/commands/create_sample_data.py
container_manager/management/commands/process_container_jobs.py
container_manager/migrations/0001_initial.py
container_manager/migrations/0002_containerjob_last_error_containerjob_last_error_at_and_more.py
container_manager/migrations/__init__.py
container_manager/static/container_manager/css/admin.css
container_manager/static/container_manager/js/admin.js
container_manager/templates/admin/container_manager/job_logs.html
container_manager/templates/admin/container_manager/queue_stats.html
container_manager/tests/__init__.py
container_manager/tests/test_job_service_integration.py
container_manager/tests/test_models_core.py
container_manager/tests/test_queue_core.py
container_manager/tests/test_services_core.py
container_manager/tests/test_state_machine_core.py
django_container_manager-1.0.14.dist-info/METADATA
django_container_manager-1.0.14.dist-info/WHEEL
django_container_manager-1.0.14.dist-info/licenses/LICENSE
django_container_manager-1.0.14.dist-info/RECORD
