Metadata-Version: 2.4
Name: django-container-manager
Version: 1.0.14
Summary: Django app for container orchestration with multi-executor support (Docker, Google Cloud Run, AWS Fargate)
Project-URL: Homepage, https://github.com/heysamtexas/django-container-manager
Project-URL: Documentation, https://github.com/heysamtexas/django-container-manager/tree/main/docs
Project-URL: Repository, https://github.com/heysamtexas/django-container-manager.git
Project-URL: Issues, https://github.com/heysamtexas/django-container-manager/issues
Project-URL: Changelog, https://github.com/heysamtexas/django-container-manager/blob/main/CHANGELOG.md
Author-email: Sam Texas <dev@simplecto.com>
Maintainer-email: Sam Texas <dev@simplecto.com>
License: MIT
License-File: LICENSE
Keywords: aws-fargate,cloud-run,containers,django,docker,job-queue,orchestration,task-runner
Classifier: Development Status :: 5 - Production/Stable
Classifier: Framework :: Django
Classifier: Framework :: Django :: 4.2
Classifier: Framework :: Django :: 5.0
Classifier: Framework :: Django :: 5.1
Classifier: Framework :: Django :: 5.2
Classifier: Intended Audience :: Developers
Classifier: License :: OSI Approved :: MIT License
Classifier: Operating System :: OS Independent
Classifier: Programming Language :: Python :: 3
Classifier: Programming Language :: Python :: 3.10
Classifier: Programming Language :: Python :: 3.11
Classifier: Programming Language :: Python :: 3.12
Classifier: Programming Language :: Python :: 3.13
Classifier: Topic :: Internet :: WWW/HTTP :: Dynamic Content
Classifier: Topic :: Software Development :: Libraries :: Python Modules
Classifier: Topic :: System :: Distributed Computing
Classifier: Topic :: System :: Systems Administration
Requires-Python: >=3.10
Requires-Dist: coverage>=7.10.0
Requires-Dist: django<6.0,>=4.2
Requires-Dist: docker>=6.0.0
Requires-Dist: google-cloud-logging>=3.12.1
Requires-Dist: psutil>=5.9.0
Provides-Extra: cloud
Requires-Dist: boto3>=1.26.0; extra == 'cloud'
Requires-Dist: google-auth>=2.0.0; extra == 'cloud'
Requires-Dist: google-cloud-run>=0.10.0; extra == 'cloud'
Provides-Extra: dev
Requires-Dist: build>=1.3.0; extra == 'dev'
Requires-Dist: coverage>=7.10.0; extra == 'dev'
Requires-Dist: django-stubs>=4.2.0; extra == 'dev'
Requires-Dist: ruff>=0.1.0; extra == 'dev'
Requires-Dist: types-requests>=2.0.0; extra == 'dev'
